intelli/__init__.py
intelli/config.py
intelli/controller/__init__.py
intelli/controller/remote_embed_model.py
intelli/controller/remote_image_model.py
intelli/controller/remote_recognition_model.py
intelli/controller/remote_speech_model.py
intelli/controller/remote_vision_model.py
intelli/flow/__init__.py
intelli/flow/dynamic_connector.py
intelli/flow/flow.py
intelli/flow/sequence_flow.py
intelli/flow/tool_connector.py
intelli/flow/types.py
intelli/flow/vibe.py
intelli/flow/agents/__init__.py
intelli/flow/agents/agent.py
intelli/flow/agents/custom_agent.py
intelli/flow/agents/handlers.py
intelli/flow/agents/kagent.py
intelli/flow/agents/speechmatics_agent.py
intelli/flow/input/__init__.py
intelli/flow/input/agent_input.py
intelli/flow/input/task_input.py
intelli/flow/processors/__init__.py
intelli/flow/processors/basic_processor.py
intelli/flow/store/__init__.py
intelli/flow/store/basememory.py
intelli/flow/store/dbmemory.py
intelli/flow/store/memory.py
intelli/flow/tasks/__init__.py
intelli/flow/tasks/loop_task.py
intelli/flow/tasks/task.py
intelli/flow/template/__init__.py
intelli/flow/template/basic_template.py
intelli/flow/utils/__init__.py
intelli/flow/utils/dynamic_utils.py
intelli/flow/utils/flow_helper.py
intelli/function/__init__.py
intelli/function/chatbot.py
intelli/mcp/__init__.py
intelli/mcp/dataframe_utils.py
intelli/mcp/utils.py
intelli/model/__init__.py
intelli/model/input/__init__.py
intelli/model/input/chatbot_input.py
intelli/model/input/embed_input.py
intelli/model/input/image_input.py
intelli/model/input/text_recognition_input.py
intelli/model/input/text_speech_input.py
intelli/model/input/vision_input.py
intelli/resource/__init__.py
intelli/resource/templates/__init__.py
intelli/resource/templates/augmented_chatbot.in
intelli/test/__init__.py
intelli/test/integration/__init__.py
intelli/test/integration/mcp_dataframe_server.py
intelli/test/integration/mcp_math_server.py
intelli/test/integration/test_anthropic_wrapper.py
intelli-1.4.5.dist-info/licenses/LICENSE
intelli-1.4.5.dist-info/METADATA
intelli-1.4.5.dist-info/WHEEL
intelli-1.4.5.dist-info/top_level.txt
intelli-1.4.5.dist-info/RECORD
