Metadata-Version: 2.4
Name: intelli
Version: 1.4.5
Summary: Build AI agents and MCPs with Intellinode.
Home-page: https://www.intellinode.ai/
Author: Intellinode
Author-email: admin@intellinode.ai
Project-URL: Source Code, https://github.com/intelligentnode/Intelli
Requires-Python: >=3.10
License-File: LICENSE
Requires-Dist: python-dotenv>=1.0.0
Requires-Dist: networkx>=3.2.0
Provides-Extra: visual
Requires-Dist: matplotlib>=3.6.0; extra == "visual"
Provides-Extra: offline
Requires-Dist: keras-nlp; extra == "offline"
Requires-Dist: keras>=3; extra == "offline"
Requires-Dist: librosa; extra == "offline"
Requires-Dist: keras-hub; extra == "offline"
Requires-Dist: tensorflow-text; extra == "offline"
Provides-Extra: llamacpp
Requires-Dist: llama-cpp-python>=0.3.7; extra == "llamacpp"
Requires-Dist: huggingface_hub>=0.28.1; extra == "llamacpp"
Provides-Extra: mcp
Requires-Dist: mcp[cli,ws]~=1.9.0; extra == "mcp"
Requires-Dist: pandas; extra == "mcp"
Provides-Extra: dataframe
Requires-Dist: pandas; extra == "dataframe"
Requires-Dist: polars>=0.19.0; extra == "dataframe"
Provides-Extra: speech
Requires-Dist: speechmatics-batch; extra == "speech"
Requires-Dist: speechmatics-rt; extra == "speech"
Requires-Dist: websockets; extra == "speech"
Requires-Dist: librosa; extra == "speech"
Requires-Dist: soundfile; extra == "speech"
Requires-Dist: numpy; extra == "speech"
Requires-Dist: openai>=2.5.0; extra == "speech"
Provides-Extra: azure-assistant
Requires-Dist: openai>=2.5.0; extra == "azure-assistant"
Provides-Extra: all
Requires-Dist: matplotlib>=3.6.0; extra == "all"
Requires-Dist: numpy<2.2.0,>=1.26.0; extra == "all"
Requires-Dist: keras-nlp; extra == "all"
Requires-Dist: keras>=3; extra == "all"
Requires-Dist: librosa; extra == "all"
Requires-Dist: keras-hub; extra == "all"
Requires-Dist: tensorflow-text; extra == "all"
Requires-Dist: llama-cpp-python>=0.3.7; extra == "all"
Requires-Dist: huggingface_hub>=0.28.1; extra == "all"
Requires-Dist: mcp[cli,ws]~=1.9.0; extra == "all"
Requires-Dist: pandas; extra == "all"
Requires-Dist: polars; extra == "all"
Requires-Dist: speechmatics-batch; extra == "all"
Requires-Dist: speechmatics-rt; extra == "all"
Requires-Dist: websockets; extra == "all"
Requires-Dist: librosa; extra == "all"
Requires-Dist: soundfile; extra == "all"
Requires-Dist: numpy; extra == "all"
Requires-Dist: openai>=2.0.0; extra == "all"
Provides-Extra: dev
Requires-Dist: pytest>=7.0.0; extra == "dev"
Dynamic: author
Dynamic: author-email
Dynamic: description
Dynamic: description-content-type
Dynamic: home-page
Dynamic: license-file
Dynamic: project-url
Dynamic: provides-extra
Dynamic: requires-dist
Dynamic: requires-python
Dynamic: summary
